appnexus/__init__.py
appnexus/client.py
appnexus/cursor.py
appnexus/exceptions.py
appnexus/model.py
appnexus/representations.py
appnexus/utils.py
AppNexus_client-0.8.1.dist-info/LICENSE
AppNexus_client-0.8.1.dist-info/METADATA
AppNexus_client-0.8.1.dist-info/WHEEL
AppNexus_client-0.8.1.dist-info/top_level.txt
AppNexus_client-0.8.1.dist-info/RECORD
