Metadata-Version: 2.1
Name: AppNexus-client
Version: 0.8.1
Summary: General purpose Python client for the AppNexus API
Home-page: https://github.com/numberly/appnexus-client
Author: numberly
Author-email: alexandre.bonnetain@1000mercis.com
License: MIT
Download-URL: https://github.com/numberly/appnexus-client/tags
Platform: any
Classifier: Intended Audience :: Developers
Classifier: Operating System :: OS Independent
Classifier: Programming Language :: Python
Classifier: Programming Language :: Python :: 2.7
Classifier: Programming Language :: Python :: 3
Classifier: Programming Language :: Python :: 3.4
Classifier: Programming Language :: Python :: 3.5
Classifier: Topic :: Software Development :: Libraries :: Python Modules
Requires-Dist: requests (>=2.20.0)
Requires-Dist: Thingy (>=0.8.3)
